imageproxy.py
imageproxy-0.2.0.dist-info/LICENSE
imageproxy-0.2.0.dist-info/METADATA
imageproxy-0.2.0.dist-info/WHEEL
imageproxy-0.2.0.dist-info/entry_points.txt
imageproxy-0.2.0.dist-info/top_level.txt
imageproxy-0.2.0.dist-info/zip-safe
imageproxy-0.2.0.dist-info/RECORD
