Metadata-Version: 2.1
Name: imageproxy
Version: 0.2.0
Summary: WSGI application to dynamically resize images.
Home-page: https://github.com/kgaughan/imageproxy
Author: Keith Gaughan
Author-email: k@stereochro.me
License: Apache Licence v2.0
Platform: UNKNOWN
Classifier: Development Status :: 2 - Pre-Alpha
Classifier: Environment :: Web Environment
Classifier: Intended Audience :: Developers
Classifier: License :: OSI Approved :: Apache Software License
Classifier: Operating System :: OS Independent
Classifier: Programming Language :: Python :: 3
Classifier: Topic :: Internet :: WWW/HTTP :: WSGI :: Application
Requires-Dist: pillow
